simple_email_confirmation/__init__.py
simple_email_confirmation/admin.py
simple_email_confirmation/exceptions.py
simple_email_confirmation/models.py
simple_email_confirmation/signals.py
simple_email_confirmation/migrations/0001_initial.py
simple_email_confirmation/migrations/__init__.py
simple_email_confirmation/south_migrations/0001_initial.py
simple_email_confirmation/south_migrations/__init__.py
simple_email_confirmation/tests/__init__.py
simple_email_confirmation/tests/tests.py
simple_email_confirmation/tests/myproject/__init__.py
simple_email_confirmation/tests/myproject/settings.py
simple_email_confirmation/tests/myproject/urls.py
simple_email_confirmation/tests/myproject/myapp/__init__.py
simple_email_confirmation/tests/myproject/myapp/models.py
django_simple_email_confirmation-0.70.dist-info/METADATA
django_simple_email_confirmation-0.70.dist-info/WHEEL
django_simple_email_confirmation-0.70.dist-info/top_level.txt
django_simple_email_confirmation-0.70.dist-info/RECORD
